docs_html_screenshot/__init__.py
docs_html_screenshot/cli.py
docs_html_screenshot-0.3.0.dist-info/METADATA
docs_html_screenshot-0.3.0.dist-info/WHEEL
docs_html_screenshot-0.3.0.dist-info/entry_points.txt
docs_html_screenshot-0.3.0.dist-info/RECORD
