Metadata-Version: 2.4
Name: docs-html-screenshot
Version: 0.3.0
Summary: CLI tool to generate full-page screenshots of static HTML files using Playwright
Project-URL: Homepage, https://github.com/pankaj28843/docs-html-screenshot
Project-URL: Bug Tracker, https://github.com/pankaj28843/docs-html-screenshot/issues
Author-email: Pankaj Singh <pankaj28843@gmail.com>
License: MIT
Classifier: Development Status :: 4 - Beta
Classifier: Environment :: Console
Classifier: Intended Audience :: Developers
Classifier: License :: OSI Approved :: MIT License
Classifier: Operating System :: OS Independent
Classifier: Programming Language :: Python :: 3
Classifier: Programming Language :: Python :: 3.10
Classifier: Programming Language :: Python :: 3.11
Classifier: Programming Language :: Python :: 3.12
Classifier: Programming Language :: Python :: 3.13
Classifier: Topic :: Documentation
Classifier: Topic :: Multimedia :: Graphics :: Capture :: Screen Capture
Requires-Python: >=3.10
Requires-Dist: click>=8.0.0
Requires-Dist: playwright>=1.55.0
Provides-Extra: dev
Requires-Dist: pytest-asyncio>=0.21.0; extra == 'dev'
Requires-Dist: pytest>=7.0.0; extra == 'dev'
Requires-Dist: ruff>=0.4.4; extra == 'dev'
